hexarray2decimal/LICENSE
hexarray2decimal/README.MD
hexarray2decimal/__init__.py
hexarray2decimal/requirements.txt
hexarray2decimal/thirdparty.json
hexarray2decimal-0.12.dist-info/LICENSE.rst
hexarray2decimal-0.12.dist-info/METADATA
hexarray2decimal-0.12.dist-info/WHEEL
hexarray2decimal-0.12.dist-info/top_level.txt
hexarray2decimal-0.12.dist-info/RECORD
